{
  "tournament_id": "692667cb52eafbbc811789f5",
  "name": "The Dark League RETURNS!!!",
  "timestamp": 1764212400000,
  "format": "Standard",
  "player_count": 31,
  "players": [
    {
      "placement": 1,
      "player_name": "Rorensu11",
      "record": "8 - 2 - 0",
      "archetype": "mega-blaziken-ex-b1-heatmor-a1"
    },
    {
      "placement": 2,
      "player_name": "oi",
      "record": "6 - 3 - 1",
      "archetype": "greninja-ex-b1-suicune-ex-a4a"
    },
    {
      "placement": 3,
      "player_name": "Uahawke",
      "record": "6 - 2 - 1",
      "archetype": "mega-absol-ex-b1-absol-a4"
    },
    {
      "placement": 4,
      "player_name": "Jayswan",
      "record": "5 - 3 - 1",
      "archetype": "mega-altaria-ex-b1-altaria-a4a"
    },
    {
      "placement": 5,
      "player_name": "Headache",
      "record": "7 - 1 - 0",
      "archetype": "greninja-ex-b1-suicune-ex-a4a"
    },
    {
      "placement": 6,
      "player_name": "KAGEKING",
      "record": "6 - 2 - 0",
      "archetype": "greninja-ex-b1-suicune-ex-a4a"
    },
    {
      "placement": 7,
      "player_name": "Ahcolvin22",
      "record": "5 - 3 - 0",
      "archetype": "decidueye-ex-a3-decidueye-a3a"
    },
    {
      "placement": 8,
      "player_name": "EllieDark",
      "record": "4 - 2 - 2",
      "archetype": "mega-altaria-ex-b1-giratina-ex-a2b"
    },
    {
      "placement": 9,
      "player_name": "IlloNico0",
      "record": "3 - 3 - 1",
      "archetype": "naganadel-a3a-mega-absol-ex-b1"
    },
    {
      "placement": 10,
      "player_name": "ClapKingJake",
      "record": "3 - 3 - 1",
      "archetype": "magnezone-a2-oricorio-a3"
    },
    {
      "placement": 11,
      "player_name": "ChemiVGC420",
      "record": "3 - 3 - 1",
      "archetype": "hydreigon-mega-absol-ex-b1"
    },
    {
      "placement": 12,
      "player_name": "J0jo0",
      "record": "3 - 3 - 0",
      "archetype": "suicune-ex-a4a-greninja-ex-b1"
    },
    {
      "placement": 13,
      "player_name": "isopod_evil_form",
      "record": "3 - 3 - 0",
      "archetype": "hydreigon-mega-absol-ex-b1"
    },
    {
      "placement": 14,
      "player_name": "Adam B",
      "record": "3 - 3 - 0",
      "archetype": "crobat-ex-a4-mega-absol-ex-b1"
    },
    {
      "placement": 15,
      "player_name": "Tobias_Oak",
      "record": "3 - 3 - 0",
      "archetype": "hydreigon-mega-absol-ex-b1"
    },
    {
      "placement": 16,
      "player_name": "Flipinton",
      "record": "1 - 5 - 0",
      "archetype": "hydreigon-mega-absol-ex-b1"
    },
    {
      "placement": 17,
      "player_name": "ELCee",
      "record": "1 - 5 - 0",
      "archetype": "mega-altaria-ex-indeedee-ex-b1"
    },
    {
      "placement": 18,
      "player_name": "Antacumbo",
      "record": "1 - 5 - 0",
      "archetype": "mega-altaria-ex-indeedee-ex-b1"
    },
    {
      "placement": 19,
      "player_name": "elmatadorperu",
      "record": "1 - 5 - 0",
      "archetype": "mega-blaziken-ex-b1-entei-ex-a4a"
    },
    {
      "placement": 20,
      "player_name": "gojiratcg",
      "record": "0 - 6 - 0",
      "archetype": "mega-altaria-ex-indeedee-ex-b1"
    },
    {
      "placement": 21,
      "player_name": "Patimivida",
      "record": "0 - 6 - 0",
      "archetype": "mega-blaziken-ex-heatmor-b1"
    },
    {
      "placement": 22,
      "player_name": "LuciferMS",
      "record": "2 - 3 - 0drop",
      "archetype": "pichu-a4-altaria-a4a"
    },
    {
      "placement": 23,
      "player_name": "iialbino",
      "record": "1 - 0 - 0drop",
      "archetype": "crobat-ex-a4-mega-absol-ex-b1"
    },
    {
      "placement": 24,
      "player_name": "Oscarparra",
      "record": "1 - 3 - 0drop",
      "archetype": "magnezone-a2-oricorio-a3"
    },
    {
      "placement": 25,
      "player_name": "SKL | Lv80Mew2.0",
      "record": "0 - 1 - 0drop",
      "archetype": "mega-ampharos-ex-b1-ampharos-a4"
    },
    {
      "placement": 26,
      "player_name": "Ktech3224",
      "record": "0 - 1 - 0drop",
      "archetype": "espeon-ex-a4-indeedee-ex-b1"
    },
    {
      "placement": 27,
      "player_name": "AraHito_makim",
      "record": "3 - 2 - 0drop",
      "archetype": "giratina-ex-a2b-darkrai-ex-a2"
    },
    {
      "placement": 28,
      "player_name": "ibi0307ibi",
      "record": "0 - 1 - 0drop",
      "archetype": "hydreigon-mega-absol-ex-b1"
    },
    {
      "placement": 29,
      "player_name": "iyla sutherland",
      "record": "2 - 3 - 0drop",
      "archetype": "greninja-ex-b1-suicune-ex-a4a"
    },
    {
      "placement": 30,
      "player_name": "kodai",
      "record": "1 - 0 - 0drop",
      "archetype": "suicune-ex-a4a-greninja-ex-b1"
    },
    {
      "placement": 31,
      "player_name": "Xari",
      "record": "0 - 2 - 0drop",
      "archetype": "espeon-ex-a4-indeedee-ex-b1"
    }
  ]
}