{
  "tournament_id": "685ca8a827d8bc24cf25b032",
  "name": "EX-treme Tournament #19 (USA)",
  "timestamp": 1751148000000,
  "format": "Standard",
  "player_count": 7,
  "players": [
    {
      "placement": 1,
      "player_name": "frappesdrinker",
      "record": "",
      "archetype": null
    },
    {
      "placement": 2,
      "player_name": "Norvey",
      "record": "",
      "archetype": null
    },
    {
      "placement": 3,
      "player_name": "Tmy2298",
      "record": "",
      "archetype": null
    },
    {
      "placement": 4,
      "player_name": "Nessii",
      "record": "",
      "archetype": null
    },
    {
      "placement": 5,
      "player_name": "Aas010690",
      "record": "",
      "archetype": null
    },
    {
      "placement": 6,
      "player_name": "yariellopezsig",
      "record": "",
      "archetype": null
    },
    {
      "placement": 7,
      "player_name": "aaron10600",
      "record": "",
      "archetype": null
    }
  ]
}