{
  "tournament_id": "690330f624b8f37ae93ca300",
  "name": "Pocket Lagoon Crew Mega Wars #1",
  "timestamp": 1761861600000,
  "format": "Standard",
  "player_count": 53,
  "players": [
    {
      "placement": 1,
      "player_name": "DNF Braver",
      "record": "8 - 1 - 0",
      "archetype": "mega-absol-ex-b1-darkrai-ex-a2"
    },
    {
      "placement": 2,
      "player_name": "iluchien",
      "record": "6 - 3 - 0",
      "archetype": "jolteon-ex-b1-pikachu-ex-a2b"
    },
    {
      "placement": 3,
      "player_name": "Fedex2729",
      "record": "5 - 2 - 1",
      "archetype": "mega-gyarados-ex-b1-milotic-a4a"
    },
    {
      "placement": 4,
      "player_name": "Lullibar",
      "record": "5 - 2 - 1",
      "archetype": "luxray-a2-oricorio-a3"
    },
    {
      "placement": 5,
      "player_name": "Crash12",
      "record": "5 - 1 - 1",
      "archetype": "entei-ex-a4a-mega-blaziken-ex-b1"
    },
    {
      "placement": 6,
      "player_name": "\ud835\udc03\ud835\udc0d\ud835\udc13 | Thanos",
      "record": "5 - 2 - 0",
      "archetype": "hydreigon-b1-sylveon-ex-a3b"
    },
    {
      "placement": 7,
      "player_name": "PattyD",
      "record": "4 - 2 - 1",
      "archetype": "mega-altaria-ex-indeedee-ex-b1"
    },
    {
      "placement": 8,
      "player_name": "Francel",
      "record": "4 - 3 - 0",
      "archetype": "entei-ex-a4a-mega-blaziken-ex-b1"
    },
    {
      "placement": 9,
      "player_name": "regenzzzeit",
      "record": "5 - 1 - 0",
      "archetype": "naganadel-guzzlord-ex-a3a"
    },
    {
      "placement": 10,
      "player_name": "joek0",
      "record": "4 - 2 - 0",
      "archetype": "mega-altaria-ex-b1-sylveon-ex-a3b"
    },
    {
      "placement": 11,
      "player_name": "\ud835\uddd4\ud835\ude02\ud835\uddff\ud835\uddfc\ud835\uddff\ud835\uddee Gravekeeper",
      "record": "3 - 2 - 1",
      "archetype": "jolteon-ex-b1-sylveon-ex-a3b"
    },
    {
      "placement": 12,
      "player_name": "NosLeakiM",
      "record": "3 - 2 - 1",
      "archetype": "jolteon-ex-b1-pikachu-ex-a2b"
    },
    {
      "placement": 13,
      "player_name": "Spectrum1227",
      "record": "3 - 2 - 1",
      "archetype": "mega-altaria-ex-b1-mismagius-a4a"
    },
    {
      "placement": 14,
      "player_name": "Dario08",
      "record": "3 - 2 - 1",
      "archetype": "jolteon-ex-b1-oricorio-a3"
    },
    {
      "placement": 15,
      "player_name": "THERIUM | KingLax",
      "record": "3 - 2 - 0drop",
      "archetype": "jolteon-ex-b1-eevee-ex-a3b"
    },
    {
      "placement": 16,
      "player_name": "kodai",
      "record": "3 - 3 - 0",
      "archetype": "mega-absol-ex-b1-darkrai-ex-a2"
    },
    {
      "placement": 17,
      "player_name": "Ayoublebg",
      "record": "3 - 2 - 0",
      "archetype": "silvally-a3a-rampardos-a2"
    },
    {
      "placement": 18,
      "player_name": "ZaydaGhost",
      "record": "3 - 2 - 0",
      "archetype": "mega-absol-ex-hydreigon-b1"
    },
    {
      "placement": 19,
      "player_name": "Revy Two Hands",
      "record": "3 - 2 - 0",
      "archetype": "mega-ampharos-ex-b1-oricorio-a3"
    },
    {
      "placement": 20,
      "player_name": "Russ_II",
      "record": "3 - 2 - 0",
      "archetype": "mega-gyarados-ex-b1-suicune-ex-a4a"
    },
    {
      "placement": 21,
      "player_name": "A_goat",
      "record": "2 - 3 - 0",
      "archetype": "charizard-ex-a2b"
    },
    {
      "placement": 22,
      "player_name": "AnHz",
      "record": "2 - 3 - 0",
      "archetype": "leafeon-ex-a2a-mega-pinsir-ex-b1"
    },
    {
      "placement": 23,
      "player_name": "Frost22",
      "record": "2 - 3 - 0drop",
      "archetype": "mega-blaziken-ex-b1-entei-ex-a4a"
    },
    {
      "placement": 24,
      "player_name": "ruiruiQ328",
      "record": "2 - 3 - 0",
      "archetype": "jolteon-ex-b1-eevee-ex-a3b"
    },
    {
      "placement": 25,
      "player_name": "Wave_Marx",
      "record": "2 - 3 - 0drop",
      "archetype": "hydreigon-b1-sylveon-ex-a3b"
    },
    {
      "placement": 26,
      "player_name": "JonnySM16",
      "record": "2 - 3 - 0",
      "archetype": "mega-altaria-ex-b1-shiinotic-a3a"
    },
    {
      "placement": 27,
      "player_name": "Gegie",
      "record": "2 - 3 - 0",
      "archetype": "entei-ex-a4a-mega-blaziken-ex-b1"
    },
    {
      "placement": 28,
      "player_name": "Acemushroom",
      "record": "2 - 2 - 0drop",
      "archetype": "mega-blaziken-ex-b1-entei-ex-a4a"
    },
    {
      "placement": 29,
      "player_name": "agustin08",
      "record": "2 - 3 - 0",
      "archetype": "suicune-ex-a4a-greninja-a1"
    },
    {
      "placement": 30,
      "player_name": "NymphNoctis",
      "record": "2 - 3 - 0",
      "archetype": "mega-gyarados-ex-gyarados-b1"
    },
    {
      "placement": 31,
      "player_name": "kaf77",
      "record": "2 - 3 - 0",
      "archetype": "jolteon-ex-b1"
    },
    {
      "placement": 32,
      "player_name": "\ud835\udc03\ud835\udc0d\ud835\udc13 | Manutan",
      "record": "2 - 3 - 0",
      "archetype": "mega-gyarados-ex-b1-milotic-a4a"
    },
    {
      "placement": 33,
      "player_name": "PGX | Chocolate",
      "record": "1 - 0 - 0drop",
      "archetype": "greninja-a1-oricorio-a3"
    },
    {
      "placement": 34,
      "player_name": "Jonah820",
      "record": "1 - 4 - 0",
      "archetype": "pachirisu-ex-a2-pikachu-ex-a2b"
    },
    {
      "placement": 35,
      "player_name": "iyla sutherland",
      "record": "1 - 3 - 0drop",
      "archetype": "greninja-a1-oricorio-a3"
    },
    {
      "placement": 36,
      "player_name": "UNAU",
      "record": "1 - 2 - 0drop",
      "archetype": "entei-ex-a4a-mega-blaziken-ex-b1"
    },
    {
      "placement": 37,
      "player_name": "Yukapower35",
      "record": "1 - 4 - 0",
      "archetype": "entei-ex-a4a-mega-blaziken-ex-b1"
    },
    {
      "placement": 38,
      "player_name": "Asadi",
      "record": "1 - 4 - 0",
      "archetype": "suicune-ex-a4a-greninja-a1"
    },
    {
      "placement": 39,
      "player_name": "Lotso27",
      "record": "1 - 3 - 0drop",
      "archetype": "mega-gyarados-ex-jellicent-b1"
    },
    {
      "placement": 40,
      "player_name": "Awbscene",
      "record": "1 - 2 - 0drop",
      "archetype": "entei-ex-a4a-mega-blaziken-ex-b1"
    },
    {
      "placement": 41,
      "player_name": "alexandergati",
      "record": "1 - 2 - 0drop",
      "archetype": "espeon-ex-a4-sylveon-ex-a3b"
    },
    {
      "placement": 42,
      "player_name": "Jirosiete",
      "record": "1 - 4 - 0",
      "archetype": "wailord-b1-mantyke-a4a"
    },
    {
      "placement": 43,
      "player_name": "Legendarykards",
      "record": "1 - 4 - 0",
      "archetype": "mega-gyarados-ex-b1-eevee-ex-a3b"
    },
    {
      "placement": 44,
      "player_name": "dakka_1988",
      "record": "0 - 2 - 0drop",
      "archetype": "espeon-ex-a4-sylveon-ex-a3b"
    },
    {
      "placement": 45,
      "player_name": "hvk",
      "record": "0 - 2 - 0drop",
      "archetype": "mega-absol-ex-b1"
    },
    {
      "placement": 46,
      "player_name": "Laquita",
      "record": "0 - 1 - 0drop",
      "archetype": "dragalge-ex-b1-darkrai-ex-a2"
    },
    {
      "placement": 47,
      "player_name": "Team_humble",
      "record": "0 - 2 - 0drop",
      "archetype": "darkrai-ex-a2-arceus-ex-a2a"
    },
    {
      "placement": 48,
      "player_name": "Merujee",
      "record": "0 - 2 - 0drop",
      "archetype": "mega-gyarados-ex-b1-gyarados-a1"
    },
    {
      "placement": 49,
      "player_name": "aiueoniisan",
      "record": "0 - 2 - 0drop",
      "archetype": "suicune-ex-a4a-greninja-ex-b1"
    },
    {
      "placement": 50,
      "player_name": "SKL | Lv80Mew2.0",
      "record": "0 - 3 - 0drop",
      "archetype": "mega-absol-ex-b1-darkrai-ex-a2"
    },
    {
      "placement": 51,
      "player_name": "pietrogatao",
      "record": "0 - 2 - 0drop",
      "archetype": "giratina-ex-a2b-darkrai-ex-a2"
    },
    {
      "placement": 52,
      "player_name": "Eclipse_tt",
      "record": "0 - 3 - 0drop",
      "archetype": "tauros-ex-b1-arceus-ex-a2a"
    },
    {
      "placement": 53,
      "player_name": "sZero | Sonder",
      "record": "0 - 1 - 0drop",
      "archetype": "entei-ex-a4a-mega-blaziken-ex-b1"
    }
  ]
}